legacystamps/__init__.py
legacystamps/legacystamps.py
legacystamps-1.2.2.data/scripts/legacystamps.py
legacystamps-1.2.2.dist-info/LICENSE
legacystamps-1.2.2.dist-info/METADATA
legacystamps-1.2.2.dist-info/WHEEL
legacystamps-1.2.2.dist-info/top_level.txt
legacystamps-1.2.2.dist-info/RECORD
