Metadata-Version: 2.1
Name: legacystamps
Version: 1.2.2
Summary: Small module to retrieve cutouts from the Legacy Survey.
Home-page: https://github.com/tikk3r/legacystamps
Author: Frits Sweijen
Author-email: frits.sweijen@gmail.com
License: UNKNOWN
Platform: UNKNOWN
Classifier: Programming Language :: Python :: 2
Classifier: Programming Language :: Python :: 3
Classifier: License :: OSI Approved :: GNU General Public License v3 (GPLv3)
Classifier: Operating System :: OS Independent
Requires-Python: >=2.7.5
Requires-Dist: requests
Requires-Dist: tqdm
